setup.py
django_quran.egg-info/PKG-INFO
django_quran.egg-info/SOURCES.txt
django_quran.egg-info/dependency_links.txt
django_quran.egg-info/top_level.txt
quran/__init__.py
quran/buckwalter.py
quran/models.py
quran/tests.py
quran/urls.py
quran/views.py
quran/data/__init__.py
quran/management/__init__.py
quran/management/commands/__init__.py
quran/management/commands/quran_loaddata.py
quran/templatetags/__init__.py
quran/templatetags/quran.py