Metadata-Version: 1.0
Name: django-quran
Version: 0.1
Summary: Quranic models and helpers for use in Django projects
Home-page: http://github.com/idris/django-quran
Author: Idris Mokhtarzada
Author-email: idris@umd.edu
License: BSD
Keywords: django quran islam arabic
Platform: UNKNOWN
Classifier: Development Status :: 3 - Alpha
Classifier: Environment :: Web Environment
Classifier: Framework :: Django
Classifier: License :: OSI Approved :: BSD License
Classifier: Operating System :: OS Independent
Classifier: Programming Language :: Python
